prefab_classes/__init__.py
prefab_classes/__init__.pyi
prefab_classes/_class_generator.py
prefab_classes/_method_generators.py
prefab_classes/_shared.py
prefab_classes/py.typed
prefab_classes/funcs/__init__.py
prefab_classes/funcs/_cache_funcs.py
prefab_classes-0.13.1.dist-info/LICENSE.md
prefab_classes-0.13.1.dist-info/METADATA
prefab_classes-0.13.1.dist-info/WHEEL
prefab_classes-0.13.1.dist-info/top_level.txt
prefab_classes-0.13.1.dist-info/RECORD
