Metadata-Version: 2.1
Name: prefab-classes
Version: 0.13.1
Summary: Boilerplate Generator for Classes
Author: David C Ellis
License: # License #
Project-URL: Homepage, https://github.com/davidcellis/PrefabClasses
Project-URL: Documentation, https://prefabclasses.readthedocs.io/
Classifier: Development Status :: 4 - Beta
Classifier: Programming Language :: Python :: 3.10
Classifier: Programming Language :: Python :: 3.11
Classifier: Programming Language :: Python :: 3.12
Classifier: Operating System :: OS Independent
Requires-Python: >=3.10
License-File: LICENSE.md
Requires-Dist: ducktools-lazyimporter >=0.2.2
Provides-Extra: build
Requires-Dist: build ; extra == 'build'
Requires-Dist: twine ; extra == 'build'
Provides-Extra: docs
Requires-Dist: sphinx ; extra == 'docs'
Requires-Dist: myst-parser ; extra == 'docs'
Requires-Dist: sphinx-rtd-theme ; extra == 'docs'
Provides-Extra: performance
Requires-Dist: attrs ; extra == 'performance'
Requires-Dist: pydantic ; extra == 'performance'
Requires-Dist: cattrs ; extra == 'performance'
Provides-Extra: testing
Requires-Dist: pytest ; extra == 'testing'
Requires-Dist: pytest-cov ; extra == 'testing'
